{
  "station_basic": {
    "stationId": 5375,
    "stationName": "SimpleWorks Solutions Pvt. Ltd.",
    "cityId": 120545,
    "city": "Nagpur",
    "accomodation": "null",
    "projectDomains": [
      190,
      5,
      65,
      127,
      29
    ],
    "preferenceNo": null,
    "isPrefered": false,
    "isOwnAccommodation": null,
    "preferredByStudent": null,
    "stationDomain": "Others",
    "state": "Maharashtra",
    "country": "India"
  },
  "station_details": {
    "stationId": 5375,
    "stationName": "SimpleWorks Solutions Pvt. Ltd.",
    "contactEstablishmentId": 2,
    "companyDescription": "<p>--</p>",
    "stationContactNumber": "7888008148",
    "websiteAddress": "simplecrm.com",
    "pstypeId": 1,
    "associationDateText": "2024",
    "incorporationYear": "2014",
    "newProblemBankExists": true,
    "problemBankExists": true,
    "otherPstypeExists": false,
    "domainId": 10,
    "subDomainId": null,
    "academicDomainId": null,
    "academicSubDomainId": null,
    "parentCompanyId": 3992,
    "parentStationName": "SimpleWorks Solutions Pvt. Ltd. (SimpleCRM)",
    "address1": "No. 10/4, STPI, IT Park, near VNIT College, Gayatri Nagar, Nagpur, Maharashtra 440022",
    "address2": " No. 10/4, STPI, IT Park, near VNIT College, Gayatri Nagar, Nagpur, Maharashtra 440022",
    "cityId": 120545,
    "stateId": 14,
    "otherCityName": null,
    "zip": "440022",
    "countryId": 1,
    "statusId": 4,
    "stationTypeId": 2,
    "stationGroupId": null,
    "reason": "",
    "relation": "",
    "assignedFacultyId": 8,
    "assignedFacultyUserName": null,
    "delete": null,
    "createdBy": "planning@bits.com",
    "stationContactName": "Snehal Wadikhaye",
    "stationContactDesignation": "Head- HR",
    "stationContactEmail": "snehal.wadikhaye@simple.works",
    "stationSpocs": [
      {
        "stationSpocId": 1241,
        "stationId": 5375,
        "salutation": null,
        "name": "Snehal Wadikhaye",
        "contactNumber": "7888008148",
        "emailAddress": "snehal.wadikhaye@simple.works",
        "designation": "Head- HR",
        "priority": null,
        "address1": "No. 10/4, STPI, IT Park, near VNIT College, Gayatri Nagar, Nagpur, Maharashtra 440022",
        "address2": " No. 10/4, STPI, IT Park, near VNIT College, Gayatri Nagar, Nagpur, Maharashtra 440022",
        "cityId": 120545,
        "stateId": 14,
        "countryId": 1,
        "isActive": 1,
        "delete": 0,
        "otherCityName": null,
        "zip": "440022",
        "cityName": null,
        "stateName": null,
        "countryName": null,
        "forBothPsTypes": false
      },
      {
        "stationSpocId": 1242,
        "stationId": 5375,
        "salutation": "Ms.",
        "name": "Snehal Wadikhaye ",
        "contactNumber": "7888008148",
        "emailAddress": "snehal.wadikhaye@simple.work",
        "designation": "(HR- Manager)",
        "priority": 2,
        "address1": "No. 10/4, STPI, IT Park, near VNIT College, ",
        "address2": "Gayatri Nagar, Nagpur, Maharashtra 440022",
        "cityId": 120545,
        "stateId": 14,
        "countryId": 1,
        "isActive": 1,
        "delete": 0,
        "otherCityName": null,
        "zip": "440022",
        "cityName": null,
        "stateName": null,
        "countryName": null,
        "forBothPsTypes": false
      }
    ],
    "centers": [],
    "stationAcademicDomains": [],
    "stationSubDomains": []
  },
  "problem_banks": [
    {
      "problem_bank": {
        "stationId": 5375,
        "stationName": "SimpleWorks Solutions Pvt. Ltd.",
        "parentStationName": "SimpleWorks Solutions Pvt. Ltd. (SimpleCRM)",
        "stationCity": "Nagpur",
        "problemBankId": 693,
        "businessDomain": "Others",
        "totalFemalRequirement": 0,
        "totalMaleRequirement": 0,
        "totalRequirement": 6,
        "noOfProject": 1,
        "batchId": 15,
        "psTypeId": 1,
        "psTypeName": "PS I",
        "semesterId": null,
        "status": null,
        "createdBy": "planning@bits.com"
      },
      "projects": []
    },
    {
      "problem_bank": {
        "stationId": 5375,
        "stationName": "SimpleWorks Solutions Pvt. Ltd.",
        "parentStationName": "SimpleWorks Solutions Pvt. Ltd. (SimpleCRM)",
        "stationCity": "Nagpur",
        "problemBankId": 2746,
        "businessDomain": "Others",
        "totalFemalRequirement": 0,
        "totalMaleRequirement": 0,
        "totalRequirement": 5,
        "noOfProject": 1,
        "batchId": 16,
        "psTypeId": 1,
        "psTypeName": "PS I",
        "semesterId": null,
        "status": null,
        "createdBy": "planning@bits.com"
      },
      "projects": []
    },
    {
      "problem_bank": {
        "stationId": 5375,
        "stationName": "SimpleWorks Solutions Pvt. Ltd.",
        "parentStationName": "SimpleWorks Solutions Pvt. Ltd. (SimpleCRM)",
        "stationCity": "Nagpur",
        "problemBankId": 8202,
        "businessDomain": "Others",
        "totalFemalRequirement": 0,
        "totalMaleRequirement": 0,
        "totalRequirement": 5,
        "noOfProject": 1,
        "batchId": 17,
        "psTypeId": 1,
        "psTypeName": "PS I",
        "semesterId": 0,
        "status": null,
        "createdBy": "planning-omprakash@bits.com"
      },
      "projects": []
    }
  ]
}