{
  "station_basic": {
    "stationId": 7025,
    "stationName": "METASRUJAN",
    "cityId": 122567,
    "city": "SY.No.119, Site No.216, Suradenpura & Basavalingappa Layout, Adde Cross, Yelahanka. Bangalore- 562110  Yelahanka. Bangalore- 562110",
    "accomodation": "null",
    "projectDomains": [
      127,
      2,
      277,
      21,
      135
    ],
    "preferenceNo": 223,
    "isPrefered": true,
    "isOwnAccommodation": 0,
    "preferredByStudent": 0,
    "stationDomain": "CSIS/IT",
    "state": "Karnataka",
    "country": "India",
    "address": null
  },
  "station_details": {
    "stationId": 7025,
    "stationName": "METASRUJAN",
    "contactEstablishmentId": 2,
    "companyDescription": "<p>--</p>",
    "stationContactNumber": "9606739715",
    "websiteAddress": "http://www.metasrujan.com/",
    "pstypeId": 1,
    "associationDateText": "2025",
    "incorporationYear": "2024",
    "newProblemBankExists": true,
    "problemBankExists": true,
    "otherPstypeExists": false,
    "domainId": 1,
    "subDomainId": null,
    "academicDomainId": null,
    "academicSubDomainId": null,
    "parentCompanyId": 5368,
    "parentStationName": "METASRUJAN",
    "address1": "SY.No.119, Site No.216, Suradenpura & Basavalingappa Layout, Adde Cross, Yelahanka. Bangalore- 562110",
    "address2": " Yelahanka. Bangalore- 562110",
    "cityId": 122567,
    "stateId": 11,
    "otherCityName": null,
    "zip": "562110",
    "countryId": 1,
    "statusId": 4,
    "stationTypeId": 2,
    "stationGroupId": 2,
    "reason": "",
    "relation": "",
    "assignedFacultyId": 41,
    "assignedFacultyUserName": null,
    "delete": null,
    "createdBy": "planning@bits.com",
    "stationContactName": "Bhavya E V ",
    "stationContactDesignation": "HR",
    "stationContactEmail": "bhavya@metasrujan.com",
    "stationSpocs": [
      {
        "stationSpocId": 1664,
        "stationId": 7025,
        "salutation": null,
        "name": "Bhavya E V ",
        "contactNumber": "9606739715",
        "emailAddress": "bhavya@metasrujan.com",
        "designation": "HR",
        "priority": null,
        "address1": "SY.No.119, Site No.216, Suradenpura & Basavalingappa Layout, Adde Cross, Yelahanka. Bangalore- 562110",
        "address2": " Yelahanka. Bangalore- 562110",
        "cityId": 122567,
        "stateId": 11,
        "countryId": 1,
        "isActive": 1,
        "delete": 0,
        "otherCityName": null,
        "zip": "562110",
        "cityName": null,
        "stateName": null,
        "countryName": null,
        "forBothPsTypes": false
      }
    ],
    "centers": [],
    "stationAcademicDomains": [],
    "stationSubDomains": []
  },
  "problem_banks": [
    {
      "problem_bank": {
        "stationId": 7025,
        "stationName": "METASRUJAN",
        "parentStationName": "METASRUJAN",
        "stationCity": "Bengaluru",
        "problemBankId": 3606,
        "businessDomain": "CSIS/IT",
        "totalFemalRequirement": 0,
        "totalMaleRequirement": 0,
        "totalRequirement": 2,
        "noOfProject": 1,
        "batchId": 16,
        "psTypeId": 1,
        "psTypeName": "PS I",
        "semesterId": null,
        "status": null,
        "createdBy": "planning@bits.com"
      },
      "projects": []
    },
    {
      "problem_bank": {
        "stationId": 7025,
        "stationName": "METASRUJAN",
        "parentStationName": "METASRUJAN",
        "stationCity": "Bengaluru",
        "problemBankId": 3607,
        "businessDomain": "CSIS/IT",
        "totalFemalRequirement": 0,
        "totalMaleRequirement": 0,
        "totalRequirement": 2,
        "noOfProject": 1,
        "batchId": 16,
        "psTypeId": 1,
        "psTypeName": "PS I",
        "semesterId": null,
        "status": null,
        "createdBy": "planning@bits.com"
      },
      "projects": []
    },
    {
      "problem_bank": {
        "stationId": 7025,
        "stationName": "METASRUJAN",
        "parentStationName": "METASRUJAN",
        "stationCity": "Bengaluru",
        "problemBankId": 3608,
        "businessDomain": "CSIS/IT",
        "totalFemalRequirement": 0,
        "totalMaleRequirement": 0,
        "totalRequirement": 2,
        "noOfProject": 1,
        "batchId": 16,
        "psTypeId": 1,
        "psTypeName": "PS I",
        "semesterId": null,
        "status": null,
        "createdBy": "planning@bits.com"
      },
      "projects": []
    },
    {
      "problem_bank": {
        "stationId": 7025,
        "stationName": "METASRUJAN",
        "parentStationName": "METASRUJAN",
        "stationCity": "Bengaluru",
        "problemBankId": 8225,
        "businessDomain": "CSIS/IT",
        "totalFemalRequirement": 0,
        "totalMaleRequirement": 0,
        "totalRequirement": 4,
        "noOfProject": 1,
        "batchId": 17,
        "psTypeId": 1,
        "psTypeName": "PS I",
        "semesterId": null,
        "status": null,
        "createdBy": "planning-sunil@bits.com"
      },
      "projects": []
    },
    {
      "problem_bank": {
        "stationId": 7025,
        "stationName": "METASRUJAN",
        "parentStationName": "METASRUJAN",
        "stationCity": "Bengaluru",
        "problemBankId": 8226,
        "businessDomain": "CSIS/IT",
        "totalFemalRequirement": 0,
        "totalMaleRequirement": 0,
        "totalRequirement": 4,
        "noOfProject": 1,
        "batchId": 17,
        "psTypeId": 1,
        "psTypeName": "PS I",
        "semesterId": null,
        "status": null,
        "createdBy": "planning-sunil@bits.com"
      },
      "projects": []
    },
    {
      "problem_bank": {
        "stationId": 7025,
        "stationName": "METASRUJAN",
        "parentStationName": "METASRUJAN",
        "stationCity": "Bengaluru",
        "problemBankId": 8227,
        "businessDomain": "CSIS/IT",
        "totalFemalRequirement": 0,
        "totalMaleRequirement": 0,
        "totalRequirement": 4,
        "noOfProject": 1,
        "batchId": 17,
        "psTypeId": 1,
        "psTypeName": "PS I",
        "semesterId": null,
        "status": null,
        "createdBy": "planning-sunil@bits.com"
      },
      "projects": []
    }
  ]
}