{
  "station_basic": {
    "stationId": 8636,
    "stationName": "Maritime Research Center, Foundation for Underwater Domain Awareeness",
    "cityId": 29,
    "city": "Maritime Research Center, G. No 365 366 368 Koregaon Bhima,  Pune, Maharashtra 412216",
    "accomodation": "null",
    "projectDomains": [
      583,
      584,
      585,
      586,
      587
    ],
    "preferenceNo": 218,
    "isPrefered": true,
    "isOwnAccommodation": 0,
    "preferredByStudent": 0,
    "stationDomain": "CSIS/IT",
    "state": "Maharashtra",
    "country": "India",
    "address": null
  },
  "station_details": {
    "stationId": 8636,
    "stationName": "Maritime Research Center, Foundation for Underwater Domain Awareeness",
    "contactEstablishmentId": 2,
    "companyDescription": "<p>--</p>",
    "stationContactNumber": "8999529110",
    "websiteAddress": "https://www.maritimeresearchcenter.com/",
    "pstypeId": 1,
    "associationDateText": "2026",
    "incorporationYear": "2019",
    "newProblemBankExists": true,
    "problemBankExists": true,
    "otherPstypeExists": false,
    "domainId": 1,
    "subDomainId": null,
    "academicDomainId": null,
    "academicSubDomainId": null,
    "parentCompanyId": 6396,
    "parentStationName": "Maritime Research Center, Foundation for Underwater Domain Awareeness",
    "address1": "Maritime Research Center, G. No 365 366 368 Koregaon Bhima, ",
    "address2": "Pune, Maharashtra 412216",
    "cityId": 29,
    "stateId": 14,
    "otherCityName": null,
    "zip": "412216",
    "countryId": 1,
    "statusId": 4,
    "stationTypeId": 6,
    "stationGroupId": 1,
    "reason": "",
    "relation": "",
    "assignedFacultyId": 741,
    "assignedFacultyUserName": null,
    "delete": null,
    "createdBy": "planning-kalyan@bits.com",
    "stationContactName": "Jay Pinjarkar",
    "stationContactDesignation": "Internship Coordinator",
    "stationContactEmail": "jay.pinjarkar@maritimeresearchcenter.com",
    "stationSpocs": [
      {
        "stationSpocId": 3372,
        "stationId": 8636,
        "salutation": null,
        "name": "Jay Pinjarkar",
        "contactNumber": "8999529110",
        "emailAddress": "jay.pinjarkar@maritimeresearchcenter.com",
        "designation": "Internship Coordinator",
        "priority": null,
        "address1": "Maritime Research Center, G. No 365 366 368 Koregaon Bhima, ",
        "address2": "Pune, Maharashtra 412216",
        "cityId": 29,
        "stateId": 14,
        "countryId": 1,
        "isActive": 1,
        "delete": 0,
        "otherCityName": null,
        "zip": "412216",
        "cityName": null,
        "stateName": null,
        "countryName": null,
        "forBothPsTypes": false
      }
    ],
    "centers": [],
    "stationAcademicDomains": [],
    "stationSubDomains": []
  },
  "problem_banks": [
    {
      "problem_bank": {
        "stationId": 8636,
        "stationName": "Maritime Research Center, Foundation for Underwater Domain Awareeness",
        "parentStationName": "Maritime Research Center, Foundation for Underwater Domain Awareeness",
        "stationCity": "Pune",
        "problemBankId": 8883,
        "businessDomain": "CSIS/IT",
        "totalFemalRequirement": 0,
        "totalMaleRequirement": 0,
        "totalRequirement": 20,
        "noOfProject": 15,
        "batchId": 17,
        "psTypeId": 1,
        "psTypeName": "PS I",
        "semesterId": null,
        "status": null,
        "createdBy": "planning-kalyan@bits.com"
      },
      "projects": []
    }
  ]
}