{
  "station_basic": {
    "stationId": 8728,
    "stationName": "PS-I Entrepreneurship track - Carbon Crunch - Non Tech",
    "cityId": 122154,
    "city": "\t Noida \t Noida",
    "accomodation": "null",
    "projectDomains": [
      81
    ],
    "preferenceNo": 286,
    "isPrefered": true,
    "isOwnAccommodation": 0,
    "preferredByStudent": 0,
    "stationDomain": "CSIS/IT",
    "state": "Uttar Pradesh",
    "country": "India",
    "address": null
  },
  "station_details": {
    "stationId": 8728,
    "stationName": "PS-I Entrepreneurship track - Carbon Crunch - Non Tech",
    "contactEstablishmentId": 3,
    "companyDescription": "<p>-</p>",
    "stationContactNumber": "0000000000",
    "websiteAddress": "www.com",
    "pstypeId": 1,
    "associationDateText": "2026",
    "incorporationYear": "2025",
    "newProblemBankExists": true,
    "problemBankExists": true,
    "otherPstypeExists": false,
    "domainId": 1,
    "subDomainId": null,
    "academicDomainId": null,
    "academicSubDomainId": null,
    "parentCompanyId": 6479,
    "parentStationName": "PS-I Entrepreneurship track - Carbon Crunch - Non Tech",
    "address1": "\t Noida",
    "address2": "\t Noida",
    "cityId": 122154,
    "stateId": 27,
    "otherCityName": null,
    "zip": "000000",
    "countryId": 1,
    "statusId": 4,
    "stationTypeId": 2,
    "stationGroupId": 1,
    "reason": "",
    "relation": "",
    "assignedFacultyId": 200,
    "assignedFacultyUserName": null,
    "delete": 0,
    "createdBy": "planning-ankita@bits.com",
    "stationContactName": "Mehul Singhvi",
    "stationContactDesignation": "-",
    "stationContactEmail": "support@carboncrunch.in",
    "stationSpocs": [
      {
        "stationSpocId": 3469,
        "stationId": 8728,
        "salutation": null,
        "name": "Mehul Singhvi",
        "contactNumber": "0000000000",
        "emailAddress": "support@carboncrunch.in",
        "designation": "-",
        "priority": null,
        "address1": "\t Noida",
        "address2": "\t Noida",
        "cityId": 122154,
        "stateId": 27,
        "countryId": 1,
        "isActive": 1,
        "delete": 0,
        "otherCityName": null,
        "zip": "000000",
        "cityName": null,
        "stateName": null,
        "countryName": null,
        "forBothPsTypes": false
      }
    ],
    "centers": [],
    "stationAcademicDomains": [],
    "stationSubDomains": []
  },
  "problem_banks": [
    {
      "problem_bank": {
        "stationId": 8728,
        "stationName": "PS-I Entrepreneurship track - Carbon Crunch - Non Tech",
        "parentStationName": "PS-I Entrepreneurship track - Carbon Crunch - Non Tech",
        "stationCity": "Noida",
        "problemBankId": 9067,
        "businessDomain": "CSIS/IT",
        "totalFemalRequirement": 0,
        "totalMaleRequirement": 0,
        "totalRequirement": 4,
        "noOfProject": 2,
        "batchId": 17,
        "psTypeId": 1,
        "psTypeName": "PS I",
        "semesterId": null,
        "status": null,
        "createdBy": "planning-ankita@bits.com"
      },
      "projects": []
    }
  ]
}